[
 {
  "table":"PERMISSION",
  "data":
  [
   {
    "CLIENT_PAK":"SCTS_HANA_OBJECT_TRANSPORT",
    "INTF_NAME":"IF_SALV_OM_PUBLIC",
    "ERR_SEVER":"NONE"
   },
   {
    "CLIENT_PAK":"SCTS_HANA_OBJECT_TRANSPORT",
    "INTF_NAME":"SABP_UNIT_TD",
    "ERR_SEVER":"NONE"
   },
   {
    "CLIENT_PAK":"SCTS_HANA_OBJECT_TRANSPORT",
    "INTF_NAME":"SNHI_API",
    "ERR_SEVER":"NONE"
   }
  ]
 },
 {
  "table":"TADIR",
  "data":
  [
   {
    "PGMID":"R3TR",
    "OBJECT":"DEVC",
    "OBJ_NAME":"SCTS_HANA_OBJECT_TRANSPORT",
    "KORRNUM":"",
    "SRCSYSTEM":"SAP",
    "AUTHOR":"SAP",
    "SRCDEP":"",
    "DEVCLASS":"SCTS_HANA_OBJECT_TRANSPORT",
    "GENFLAG":"",
    "EDTFLAG":"",
    "CPROJECT":" S",
    "MASTERLANG":"D",
    "VERSID":"0.0",
    "PAKNOCHECK":"",
    "OBJSTABLTY":"",
    "COMPONENT":"SAP_BASIS",
    "CRELEASE":"740",
    "DELFLAG":"",
    "TRANSLTTXT":"",
    "CREATED_ON":"2014-02-24",
    "CHECK_DATE":"2014-02-24",
    "CHECK_CFG":""
   }
  ]
 },
 {
  "table":"TDEVC",
  "data":
  [
   {
    "DEVCLASS":"SCTS_HANA_OBJECT_TRANSPORT",
    "INTSYS":"SAP",
    "CONSYS":"SAP",
    "CTEXT":"",
    "KORRFLAG":"X",
    "AS4USER":"SAP",
    "PDEVCLASS":"SAP",
    "DLVUNIT":"SAP_BASIS",
    "COMPONENT":"BYI3001331",
    "NAMESPACE":"/0SAP/",
    "TPCLASS":"X",
    "SHIPMENT":"",
    "PARENTCL":"SCTS_HANA_OBJECT_TRANSPRT_MAIN",
    "APPLICAT":"",
    "ERRSEVRTY":"",
    "PERMINHER":"",
    "INTFPREFX":"",
    "PACKTYPE":"",
    "RESTRICTED":"",
    "MAINPACK":"",
    "CREATED_BY":"SAP",
    "CREATED_ON":"2014-02-24",
    "CHANGED_BY":"SAP",
    "CHANGED_ON":"2015-03-24",
    "SRV_CHECK":"",
    "CLI_CHECK":"",
    "EXT_ALIAS":"",
    "PROJECT_GUID":"",
    "PROJECT_PASSDOWN":"",
    "IS_ENHANCEABLE":"",
    "PACKAGE_KIND":"",
    "ENHANCED_PACKAGE":"",
    "ACCESS_OBJECT":"",
    "DEFAULT_INTF":"",
    "INHERIT_CLI_INTF":"",
    "TECH_CHG_TSTMP":"0",
    "OVERALL_TSTMP":"0",
    "ENCAPSULATION":"",
    "DCL_ENABLED":"",
    "SUB_KEY":"",
    "ALLOW_STATIC":"",
    "SWITCH_ID":"",
    "CHECK_RULE":""
   }
  ]
 },
 {
  "table":"TDEVCT",
  "data":
  [
   {
    "DEVCLASS":"SCTS_HANA_OBJECT_TRANSPORT",
    "SPRAS":"D",
    "CTEXT":"HANA-Repository-Objekttransport für ABAP on HANA"
   },
   {
    "DEVCLASS":"SCTS_HANA_OBJECT_TRANSPORT",
    "SPRAS":"E",
    "CTEXT":"HANA Repository Object Transport for ABAP on HANA"
   }
  ]
 }
]